{
  "id": "ACIMU",
  "nombre": "ACIDO MUCONICO (Benceno) EN ORINA",
  "codigoCups": "905758",
  "slug": "acido-muconico-benceno-en-orina",
  "categoria": "quimica",
  "diaProceso": "VIERNES",
  "oportunidadResultados": "10 dias habiles a partir del día de procesamiento",
  "muestra": "Orina al azar. Enviar alicuota. (50 mL)",
  "preparacion": "Orina al azar recogida después de la jornada laboral; mantener refrigerada posterior a la recolección.",
  "nombresAlternativos": [],
  "sedesDisponibles": [],
  "examenesRelacionados": [],
  "perfiles": [],
  "requiereAyuno": false,
  "imagen": null,
  "activo": true
}
