{
  "id": "902024",
  "mongoId": "635afd054d2fd1d313dd4c21",
  "nombre": "FIBRINOGENO ",
  "codigoCups": "902024",
  "slug": "fibrinogeno",
  "categoria": "hematologia",
  "nombresAlternativos": [],
  "requiereAyuno": false,
  "preparacion": "No requiere ninguna preparación especial previa. Relacionar datos clínicos del paciente en la solicitud.",
  "oportunidadResultados": "72 horas a partir del día de procesamiento.",
  "sedesDisponibles": [],
  "examenesRelacionados": [],
  "perfiles": [],
  "imagen": null,
  "activo": true
}
