{
  "id": "903834",
  "mongoId": "635afd054d2fd1d313dd4c26",
  "nombre": "FOSFATASA ALCALINA ESPECIFICA DE HUESO",
  "codigoCups": "903834",
  "slug": "fosfatasa-alcalina-especifica-de-hueso",
  "categoria": "quimica",
  "nombresAlternativos": [],
  "requiereAyuno": false,
  "preparacion": "No requiere ninguna preparación especial previa. Relacionar datos clínicos del paciente en la solicitud.",
  "oportunidadResultados": "8 días hábiles a partir de la fecha de envío a la red de apoyo internacional.",
  "sedesDisponibles": [],
  "examenesRelacionados": [],
  "perfiles": [],
  "imagen": null,
  "activo": true
}
