{
  "id": "HVC-CUANT",
  "nombre": "Hepatitis C ANTICUERPO AUTOMATIZADO",
  "codigoCups": "906225",
  "slug": "hepatitis-c-anticuerpo-automatizado",
  "categoria": "inmunologia-infecciosa",
  "diaProceso": "LUNES A VIERNES",
  "oportunidadResultados": "3 Dias a partir del día de procesamiento",
  "muestra": "Suero (1.0mL)",
  "preparacion": "No requiere ninguna preparación especial previa Relacionar datos clínicos del paciente en la Solicitud",
  "nombresAlternativos": [],
  "sedesDisponibles": [],
  "examenesRelacionados": [],
  "perfiles": [],
  "requiereAyuno": false,
  "imagen": null,
  "activo": true
}
