{
  "id": "MERO24",
  "nombre": "MERCURIO AUTOMATIZADO (ORINA DE 24H.)",
  "codigoCups": "905731",
  "slug": "mercurio-automatizado-orina-de-24h",
  "categoria": "toxicologia",
  "diaProceso": "MIERCOLES Y VIERNES",
  "oportunidadResultados": "7 días hábiles a partir del dia de procesamiento",
  "muestra": "Orina 24 horas alicuota (30.0mL)",
  "preparacion": "No requiere ninguna preparación especial previa Relacionar datos clínicos del paciente en la Solicitud Refrigerar durante y después de la recolección",
  "nombresAlternativos": [],
  "sedesDisponibles": [],
  "examenesRelacionados": [],
  "perfiles": [],
  "requiereAyuno": false,
  "imagen": null,
  "activo": true
}
