{
  "id": "PRLPE",
  "nombre": "PROLACTINA PRE Y POST ESTIMULACION",
  "codigoCups": "904204",
  "slug": "prolactina-pre-y-post-estimulacion",
  "categoria": "hormonas",
  "diaProceso": "Viernes",
  "oportunidadResultados": "24 horas a partir del día de procesamiento",
  "muestra": "Suero (2.0mL)",
  "preparacion": "Paciente en ayuno. Se realiza toma de muestra de acuerdo a lo indicado por la orden medica. Relacionar datos clínicos del paciente en la Solicitud",
  "nombresAlternativos": [],
  "sedesDisponibles": [],
  "examenesRelacionados": [],
  "perfiles": [],
  "requiereAyuno": false,
  "imagen": null,
  "activo": true
}
