{
  "id": "906454",
  "mongoId": "635afd054d2fd1d313dd4d21",
  "nombre": "SSA [Ro] ANTICUERPOS SEMIAUTOMATIZADO ",
  "codigoCups": "906454",
  "slug": "ssa-ro-anticuerpos-semiautomatizado",
  "categoria": "hormonas",
  "nombresAlternativos": [],
  "requiereAyuno": false,
  "preparacion": "No requiere ninguna preparación especial previa Relacionar datos clínicos del paciente en la Solicitud",
  "oportunidadResultados": "24 horas a partir del día de procesamiento",
  "sedesDisponibles": [],
  "examenesRelacionados": [],
  "perfiles": [],
  "imagen": null,
  "activo": true
}
